opoint/py.typed
opoint/safefeed/aio.py
opoint/safefeed/api.py
opoint/safefeed/common.py
opoint/safefeed/sync.py
opoint-0.1.2.dist-info/METADATA
opoint-0.1.2.dist-info/WHEEL
opoint-0.1.2.dist-info/RECORD
