Metadata-Version: 2.4
Name: opoint
Version: 0.1.2
Summary: Client library for Opoint products
Author-email: Karl Erik Hofseth <karl.e.hofseth@infomedia.dk>
License-Expression: GPL-3.0-or-later
Requires-Python: >=3.12
Provides-Extra: aio
Requires-Dist: aiohttp[speedups]>=3.11.11; extra == 'aio'
Requires-Dist: asyncio>=3.4.3; extra == 'aio'
Provides-Extra: requests
Requires-Dist: requests>=2.32.3; extra == 'requests'
